odoo/addons/partner_company_group/README.rst
odoo/addons/partner_company_group/__init__.py
odoo/addons/partner_company_group/__manifest__.py
odoo/addons/partner_company_group/i18n/ca.po
odoo/addons/partner_company_group/i18n/ca_ES.po
odoo/addons/partner_company_group/i18n/es.po
odoo/addons/partner_company_group/i18n/it.po
odoo/addons/partner_company_group/i18n/partner_company_group.pot
odoo/addons/partner_company_group/models/__init__.py
odoo/addons/partner_company_group/models/account_invoice.py
odoo/addons/partner_company_group/models/crm_lead.py
odoo/addons/partner_company_group/models/res_partner.py
odoo/addons/partner_company_group/models/sale_order.py
odoo/addons/partner_company_group/readme/CONTRIBUTORS.rst
odoo/addons/partner_company_group/readme/DESCRIPTION.rst
odoo/addons/partner_company_group/static/description/icon.png
odoo/addons/partner_company_group/static/description/index.html
odoo/addons/partner_company_group/tests/__init__.py
odoo/addons/partner_company_group/tests/test_partner_company_group.py
odoo/addons/partner_company_group/views/account_invoice_view.xml
odoo/addons/partner_company_group/views/contact_view.xml
odoo/addons/partner_company_group/views/opportunity_view.xml
odoo/addons/partner_company_group/views/sale_order_view.xml
odoo12_addon_partner_company_group-12.0.1.2.1.dist-info/METADATA
odoo12_addon_partner_company_group-12.0.1.2.1.dist-info/WHEEL
odoo12_addon_partner_company_group-12.0.1.2.1.dist-info/top_level.txt
odoo12_addon_partner_company_group-12.0.1.2.1.dist-info/RECORD
